snellscore.py
snellscore-1.1.0.dist-info/LICENSE
snellscore-1.1.0.dist-info/METADATA
snellscore-1.1.0.dist-info/WHEEL
snellscore-1.1.0.dist-info/top_level.txt
snellscore-1.1.0.dist-info/RECORD
