Metadata-Version: 2.2
Name: snellscore
Version: 1.1.0
Summary: An Python implementation for Snell scoring
Author-email: Igor <igor.loschinin@gmail.com>
License: GNU
Project-URL: Homepage, https://github.com/IgorekLoschinin/snellscore
Requires-Python: >=3.10
License-File: LICENSE
Requires-Dist: numpy>=2.2.1
Requires-Dist: pandas>=2.2.3
Requires-Dist: pytest>=8.3.4
